{"owner":{"reputation":719,"user_id":327955,"user_type":"registered","profile_image":"https://lh5.googleusercontent.com/-zn4A4d_oBCU/AAAAAAAAAAI/AAAAAAAAAAA/ACevoQP7uit0xJANPoEE96j7UkZChM-yAQ/mo/photo.jpg?sz=128","display_name":"mathem","link":"https://ru.meta.stackoverflow.com/users/327955/mathem"},"score":1,"last_edit_date":1578491530,"last_activity_date":1578518952,"creation_date":1578489829,"post_type":"question","post_id":9979,"link":"https://ru.meta.stackoverflow.com/q/9979","body":"<p>Так, стало интересно. Почему никто не голосует по этим вопросам? Пишу, можно сказать, эксклюзив: поди, найди в Рунете инфу про LyX, а репутация стоит на месте. </p>\n\n<p>Мне, конечно, скоро она будет почти постольку-поскольку: просто расскажу всё, что знаю про эту прогу, а больше на компьютерном форуме мне рассказывать не о чем, но тем не менее...</p>\n"}