{"owner":{"reputation":11,"user_id":367268,"user_type":"registered","profile_image":"https://www.gravatar.com/avatar/d3bc2c633a2c9c286ded6358033cffe7?s=128&d=identicon&r=PG&f=1","display_name":"TimmmofeyD","link":"https://ru.meta.stackoverflow.com/users/367268/timmmofeyd"},"is_accepted":false,"score":2,"last_activity_date":1578725306,"creation_date":1578725306,"answer_id":10006,"question_id":10005,"body":"<p>Полностью солидарен.Заходите в свой профиль, там есть вкладка править и внизу будет удаление.</p>\n"}