{"owner":{"reputation":16058,"user_id":240512,"user_type":"registered","profile_image":"https://i.stack.imgur.com/Ew6lG.png?s=128&g=1","display_name":"MSDN.WhiteKnight","link":"https://ru.stackoverflow.com/users/240512/msdn-whiteknight"},"is_accepted":true,"score":16,"last_activity_date":1533708690,"creation_date":1533708690,"answer_id":865806,"question_id":865803,"body":"<p>Второй метод является <a href=\"https://docs.microsoft.com/en-us/dotnet/csharp/programming-guide/interfaces/explicit-interface-implementation\" rel=\"noreferrer\">явной реализацией интерфейса</a>, так что все нормально. Он будет вызван только при явном приведении типа <code>SomeType</code> к <code>IDisposable</code>, тогда как первый метод будет вызываться при работе напрямую с <code>SomeType</code>.</p>\n"}