{"owner":{"reputation":90832,"user_id":178988,"user_type":"moderator","accept_rate":72,"profile_image":"https://www.gravatar.com/avatar/cbfaff96665b7567defe1b34a883db8b?s=128&d=identicon&r=PG","display_name":"Qwertiy","link":"https://ru.stackoverflow.com/users/178988/qwertiy"},"is_accepted":false,"score":1,"last_activity_date":1462911752,"last_edit_date":1462911752,"creation_date":1462910754,"answer_id":522220,"question_id":522218,"body":"<p>Если программа 32-битная, а адрес отрицательный и система не запущена в режиме <code>/3GB</code> или программа, в которой определялся адрес не поддерживает работу в этом режиме, то он будет одинаков во всех процессах. Здесь имеется в виду именно одинаковость для разных процессов, но не константность адреса.</p>\n\n<p>По крайней мере, я так думаю.</p>\n\n<p><a href=\"http://bbs.vbstreets.ru/viewtopic.php?p=6784461#p6784461\" rel=\"nofollow\">Подробнее о памяти в Windows.</a></p>\n"}