{"owner":{"reputation":22878,"user_id":32793,"user_type":"registered","accept_rate":48,"profile_image":"https://i.stack.imgur.com/6Vktl.jpg?s=128&g=1","display_name":"iluxa1810","link":"https://ru.stackoverflow.com/users/32793/iluxa1810"},"is_accepted":false,"score":1,"last_activity_date":1550040434,"last_edit_date":1550040434,"creation_date":1550039072,"answer_id":944201,"question_id":943811,"body":"<p>Можно сделать так:</p>\n\n<ol>\n<li>Пишем программу, которая ходит по компьютерам в сети и через WMI,\nлибо реестр и собирает информацию о машинах и записывает в\nкакой-нибудь txt-файл. 1 машина-1 файл.</li>\n<li>На какой-нибудь 1 машине настраиваем планировщик задач, что бы он запускал программу из под высокопревелигированной учетки и время от времени перезаписывал(актуализировал) данные.</li>\n</ol>\n\n<p>В итоге получается, что программа запускается по расписанию и кладет данные на общую шару и любой пользователь обладающий доступ на чтение, может открыть необходимый TXT и увидеть нужную информацию.</p>\n\n<p>И проблем с безопасностью никаких не будет.</p>\n\n<p>Ну это самый простой вариант. Решение \"по взрослому\"- это написать сервис к которому будут обращаться пользователи. А сам сервис будет иметь админские права и делать то, что я описал в первых пунктах.</p>\n"}