{"owner":{"reputation":16058,"user_id":240512,"user_type":"registered","profile_image":"https://i.stack.imgur.com/Ew6lG.png?s=128&g=1","display_name":"MSDN.WhiteKnight","link":"https://ru.stackoverflow.com/users/240512/msdn-whiteknight"},"is_accepted":false,"score":4,"last_activity_date":1552064378,"last_edit_date":1552064378,"creation_date":1552055346,"answer_id":954025,"question_id":954009,"body":"<p>char в C# - это value type, он не может иметь пустое значение, поэтому такая проверка не имеет смысла. Неинициализированная переменная типа char содержит его значение по умолчанию (символ <code>\\0</code>). Если вам нужен тип, который может хранить либо символ, либо специальное пустое значение, смотрите в сторону <a href=\"https://docs.microsoft.com/en-us/dotnet/csharp/programming-guide/nullable-types/\" rel=\"nofollow noreferrer\">Nullable types</a></p>\n"}